beancount_bot_costflow/__init__.py
beancount_bot_costflow/beancount_bot_costflow.py
beancount_bot_costflow/costflow-parser.js
beancount_bot_costflow-1.1.0.dist-info/LICENSE
beancount_bot_costflow-1.1.0.dist-info/METADATA
beancount_bot_costflow-1.1.0.dist-info/WHEEL
beancount_bot_costflow-1.1.0.dist-info/top_level.txt
beancount_bot_costflow-1.1.0.dist-info/RECORD
