Metadata-Version: 2.1
Name: beancount-bot-costflow
Version: 1.1.0
Summary: A plugin adds costflow syntax supports for beancount_bot
Home-page: https://github.com/kaaass/beancount_bot_costflow
Author: KAAAsS
Author-email: admin@kaaass.net
License: GPLv3
Platform: UNKNOWN
Classifier: Programming Language :: Python :: 3
Classifier: License :: OSI Approved :: MIT License
Classifier: Operating System :: OS Independent
License-File: LICENSE
Requires-Dist: beancount-bot (>=1.0.1)
